neural_boost/__init__.py
neural_boost/gru.py
neural_boost/libneural_boost.so
neural_boost/lstm.py
neural_boost/nb.py
neural_boost-0.0.5.dist-info/LICENSE
neural_boost-0.0.5.dist-info/METADATA
neural_boost-0.0.5.dist-info/WHEEL
neural_boost-0.0.5.dist-info/top_level.txt
neural_boost-0.0.5.dist-info/RECORD
